font_rename.py
font_rename-0.2.0.dist-info/entry_points.txt
font_rename-0.2.0.dist-info/LICENSE
font_rename-0.2.0.dist-info/WHEEL
font_rename-0.2.0.dist-info/METADATA
font_rename-0.2.0.dist-info/RECORD
